{"name":"mojito-echarts","version":"1.0.0","external":{"echarts":"http://cdn.staticfile.org/echarts/5.4.3/echarts.min.js"},"components":[{"exportName":"AreaLine","name":"基础面积图","category":"折线图","cover":"/public/mojito-echarts@1.0.0/3f7bb44e777e23e84924.webp"},{"exportName":"BarChart","name":"基本柱状图","category":"柱状图","cover":"/public/mojito-echarts@1.0.0/71e7def816557e2fabc9.webp"},{"exportName":"BarChartY","name":"基础条形图","category":"柱状图","cover":"/public/mojito-echarts@1.0.0/ff6100b924c1c2c4df26.webp"},{"exportName":"Doughnut","name":"环形图","category":"饼图","cover":"/public/mojito-echarts@1.0.0/23a4470d2cdcc50a4692.webp"},{"exportName":"LineChart","name":"基础折线图","category":"折线图","cover":"/public/mojito-echarts@1.0.0/2aa2d4168477199bed22.webp"},{"exportName":"MultipleBar","name":"分类柱状图","category":"柱状图","cover":"/public/mojito-echarts@1.0.0/5fe8a2bc3d8f1e408902.webp"},{"exportName":"MultipleBarY","name":"分类条形图","category":"柱状图","cover":"/public/mojito-echarts@1.0.0/e4e3bb7a81299a37197b.webp"},{"exportName":"PieChart","name":"基础饼图","category":"饼图","cover":"/public/mojito-echarts@1.0.0/44cbfc52ec7613a3cb67.webp"},{"exportName":"Rose","name":"南丁格尔玫瑰图","category":"饼图","cover":"/public/mojito-echarts@1.0.0/3c879890e73ac9c9bd2b.webp"},{"exportName":"ScatterChart","name":"基础散点图","category":"散点图","cover":"/public/mojito-echarts@1.0.0/e24b293aa4176fae4852.webp"},{"exportName":"StackBar","name":"堆叠柱状图","category":"柱状图","cover":"/public/mojito-echarts@1.0.0/0a1d87669985d6202e18.webp"},{"exportName":"StackBarY","name":"堆叠条形图","category":"柱状图","cover":"/public/mojito-echarts@1.0.0/25611c2adfe3bc7cb15c.webp"},{"exportName":"StackLine","name":"堆叠折线图","category":"折线图","cover":"/public/mojito-echarts@1.0.0/41527d43c039a4773505.webp"}]}